Workbook

Sheet Executive Summary
A1: REELSTORM EXPENDITURE & REVENUE ARTIFACT
A2: Captain tier system · Soft-launch ready · Generated for ReelStorm Academy OS
A4: UNIT RULES
A5: 1 RTC = 1 minute finished master @ 720p
A6: 1 SET = 5-min ARCHIVE5 = 5 RTC
A7: Cost / set 720p (Cost Saver) | B7: =Assumptions!B30
A8: Cost / RTC 720p | B8: =Assumptions!B31
A9: Cost / set 1080p | B9: =Assumptions!B32
A11: LAUNCH TIERS
A12: Tier | B12: Price | C12: Sets | D12: RTC | E12: Res | F12: Role
A13: Free Test | B13: $0 | C13: — | D13: 1 | E13: 480p | F13: Hook · no download
A14: Basic | B14: $49/mo | C14: 3 | D14: 15 | E14: 720p only | F14: Margin lock
A15: Premium ★ | B15: $99/mo | C15: 5 | D15: 25 | E15: 1080p | F15: YouTuber hero
A16: Premium Pro | B16: $199/mo | C16: 10 | D16: 50 | E16: 1080p+ | F16: DNA · team · rollover
A17: Network | B17: Custom | C17: negotiated | D17: pool | E17: 1080p | F17: White-label B2B
A19: MUST-PAY APIs (see API Subscriptions sheet)
A20: 1. DashScope Qwen — LLM
A21: 2. Seedance (via DashScope) — video clips (largest COGS)
A22: 3. Supabase Pro — Auth + DB
A23: 4. Stripe — billing
A24: 5. Cloudflare R2 — media storage
A25: 6. IONOS VPS — compute / workers / Ollama
A26: Optional: ElevenLabs, Kling, Veo
A28: PORTFOLIO SNAPSHOT (edit counts on Portfolio Scenario)
A29: Subscription MRR | B29: ='Portfolio Scenario'!C10
A30: Subscription COGS | B30: ='Portfolio Scenario'!D10
A31: Gross profit (subs) | B31: ='Portfolio Scenario'!E10
A32: Fixed platform opex | B32: ='API Subscriptions'!E20
A33: Net monthly (incl packs − opex) | B33: ='Portfolio Scenario'!D17
A35: CAPTAIN GUARDRAILS
A36: • Lock Basic to 720p forever — prevents margin bleed
A37: • Free = no download; watermark; 24h expiry
A38: • Prefer Cost Saver (5s clips) in BOT Wizard — halves Seedance spend
A39: • Soft-cap Premium 1080p if full-use stress shows BLEED
A40: • Overage packs are the viral-month profit engine

Sheet Assumptions
A1: REELSTORM — Expenditure & Revenue Model
A2: Based on Captain tier system · 1 RTC = 1 min master (720p) · 1 set = 5 RTC
A3: Blue cells = editable inputs · Black = formulas · Yellow = key levers · Source: Captain cost model (session)
A5: UNIT ECONOMICS LEVERS
A6: Key | B6: Value | C6: Unit | D6: Notes
A7: cost_per_clip_720 | B7: 0.3 | C7: USD | D7: Seedance/Kling ~5s clip @ 720p — Source: Captain model
A8: clips_per_5min_set_saver | B8: 30 | C8: clips | D8: Cost Saver path: 5s clips
A9: clips_per_5min_set_cinema | B9: 15 | C9: clips | D9: Cinematic path: 10s clips (half count)
A10: cost_script_llm | B10: 0.02 | C10: USD | D10: DashScope Qwen loglines
A11: cost_world_bible | B11: 0.4 | C11: USD | D11: DashScope + vision plates
A12: cost_first_frames | B12: 0.12 | C12: USD | D12: DashScope image × 6
A13: cost_voice_5min | B13: 0.81 | C13: USD | D13: ElevenLabs optional VO ~750 words
A14: cost_sfx | B14: 0.3 | C14: USD | D14: SFX / score bed
A15: cost_merge_r2 | B15: 0.15 | C15: USD | D15: ffmpeg + R2 storage
A16: cost_worker | B16: 0.2 | C16: USD | D16: VPS BullMQ share
A17: rtc_per_set | B17: 5 | C17: RTC | D17: 1 set = 5 min = 5 RTC
A18: sell_per_rtc_implied | B18: 7.99 | C18: USD | D18: Standalone RTC list (packs discount)
... A24: mix_premium_1080 | B24: 0.5 | C24: fraction | D24: Share of Premium minutes rendered 1080p
A27: DERIVED COST PER 5-MIN SET (720p Cost Saver)
A28: Video gen | B28: =B7*B8
A29: Non-video stack | B29: =B10+B11+B12+B13+B14+B15+B16
A30: TOTAL cost / set 720p | B30: =B28+B29
A31: Cost / RTC 720p | B31: =B30/B17
A32: TOTAL cost / set 1080p | B32: =B29+(B28*B19)
A33: Cost / RTC 1080p | B33: =B32/B17
A34: Cinematic clip path cost (720p) | B34: =(B7*B9)+B29 | C34: Half the clips → ~half video spend
A36: EDIT GUIDE
A37: Change yellow/blue inputs only. All other sheets pull from Assumptions!B7:B24 and B30:B33.

Sheet API Subscriptions
A1: API & PLATFORM SUBSCRIPTIONS (Expenditure)
A2: What ReelStorm pays vendors monthly (fixed) + usage-variable notes. Blue = editable fixed fees.
A4: Service | B4: Role in factory | C4: Env / plan | D4: Billing model | E4: Est. fixed $/mo | F4: Variable driver | G4: Required? | H4: Notes
A5: Alibaba DashScope (Qwen) | B5: LLM orchestration · loglines · world bible · first frames | C5: DASHSCOPE_API_KEY · Qwen-Plus | D5: Pay-as-you-go tokens | E5: 0 | F5: Tokens / images | G5: Yes (or Ollama) | H5: Soft launch can use local Ollama
A6: DashScope Seedance / Seedance API | B6: Video clip generation (monster cost) | C6: SEEDANCE_API_KEY or DashScope | D6: Per-clip / per-second | E6: 0 | F6: Clips × duration × res | G6: Yes for real video | H6: ~$0.30/5s clip @ 720p — Captain
A7: Kling AI (optional) | B7: Video fallback | C7: KLING_API_KEY | D7: Pay-as-you-go | E7: 0 | F7: Clips | G7: Optional | H7: Tier C
A8: Google Veo (optional) | B8: Premium video path | C8: VEO_API_KEY / GOOGLE_API_KEY | D8: Pay-as-you-go | E8: 0 | F8: Clips | G8: Optional / Storm Pro+ | H8: Premium path only
A9: ElevenLabs (optional) | B9: Voice clone · TTS under Sound Studio | C9: ELEVENLABS_API_KEY · Creator/Pro | D9: Chars / seats | E9: 22 | F9: Characters spoken | G9: Optional | H9: ~$0.18/1k chars; Sound Studio owns surface
A10: Supabase | B10: Auth + Postgres | C10: SUPABASE_* · Pro plan @ 1k users | D10: Subscription | E10: 25 | F10: MAU / DB / storage | G10: Yes | H10: Upgrade off Free before ~1k users
A11: Google OAuth | B11: Gmail sign-in | C11: GOOGLE_CLIENT_ID | D11: Free | E11: 0 | F11: — | G11: Yes | H11: Configured in Supabase Auth
A12: Stripe | B12: Subscriptions + RTC packs + webhook | C12: STRIPE_SECRET_KEY sk_live_/sk_test_ | D12: % + fixed / txn | E12: 0 | F12: 2.9% + $0.30 typical | G12: Yes | H12: Basic $49 · Premium $99 · Pro $199
A13: Cloudflare R2 (or AWS S3) | B13: Object storage for masters / uploads | C13: S3_* / R2_* | D13: Storage + egress | E13: 5 | F13: GB stored / egress | G13: Yes @ scale | H13: Replace MinIO staging
A14: IONOS VPS | B14: API · Worker · Web · Redis · Ollama | C14: Host 87.106… ports 3017/4017 | D14: VPS monthly | E14: 40 | F14: CPU hours / concurrency | G14: Yes | H14: WORKER_CONCURRENCY≥8
A15: Redis (on VPS) | B15: BullMQ queues db 17 | C15: REDIS_URL | D15: Included in VPS | E15: 0 | F15: Jobs | G15: Yes | H15: BULLMQ_PREFIX=reelstorm
A16: Domain + SSL | B16: reelstorm.uk · app · api | C16: DNS / certbot | D16: Domain yearly amortized | E16: 2 | F16: — | G16: Yes | H16: Nginx multi-tenant safe
... A18: ffmpeg / yt-dlp | B18: Analyze · split · merge · URL extract | C18: System binaries | D18: Included | E18: 0 | F18: CPU / disk | G18: Yes | H18: ≥50 GiB upload volume
A20: TOTAL fixed platform $/mo | E20: =SUM(E5:E18)
A22: VARIABLE COGS (not in fixed total)
A23: Primary variable spend = Seedance/Kling video clips + optional ElevenLabs chars + R2 egress. Modeled per set on Assumptions & Tier P&L sheets.

Sheet Tier P&L
A1: TIER REVENUE vs EXPENDITURE (per subscriber / month)
A2: Cost uses Assumptions derived set cost × avg utilization. Premium mixes 720p/1080p via mix_premium_1080.
A4: Tier | B4: Price $/mo | C4: Sets incl. | D4: RTC incl. | E4: Max res | F4: Avg use % | G4: Sets used (avg) | H4: COGS $/sub | I4: Gross margin $ | J4: Gross margin % | K4: Target
A5: Free Test | B5: 0 | C5: 0 | D5: 1 | E5: 480p | F5: 1 | G5: 0.2 | H5: =Assumptions!$B$31*D5 | I5: =B5-H5 | J5: =IF(B5=0,"n/a CAC",I5/B5) | K5: Hook / FOMO
A6: Basic | B6: 49 | C6: 3 | D6: 15 | E6: 720p only | F6: =Assumptions!B20 | G6: =C6*F6 | H6: =Assumptions!$B$30*G6 | I6: =B6-H6 | J6: =IF(B6=0,0,I6/B6) | K6: Ad shops · testers
A7: Premium ★ | B7: 99 | C7: 5 | D7: 25 | E7: 1080p unlock | F7: =Assumptions!B21 | G7: =C7*F7 | H7: =G7*((1-Assumptions!$B$24)*Assumptions!$B$30+Assumptions!$B$24*Assumptions!$B$32) | I7: =B7-H7 | J7: =IF(B7=0,0,I7/B7) | K7: YouTuber hero
A8: Premium Pro | B8: 199 | C8: 10 | D8: 50 | E8: 1080p native | F8: =Assumptions!B22 | G8: =C8*F8 | H8: =G8*Assumptions!$B$32 | I8: =B8-H8 | J8: =IF(B8=0,0,I8/B8) | K8: Artists · ads · DNA
A9: Network (WL) | B9: 0 | C9: 40 | D9: 200 | E9: 1080p | F9: 0.5 | G9: =C9*F9 | H9: =G9*Assumptions!$B$30 | I9: =B9-H9 | J9: =IF(B9=0,"Custom quote",I9/B9) | K9: Academies B2B
A11: FULL-USE STRESS (100% RTC burn — worst month)
A12: Tier | B12: COGS if 100% use | C12: Margin $ | D12: Verdict
A13: Basic 720p | B13: =3*Assumptions!$B$30 | C13: =49-B13 | D13: =IF(C13>0,"OK lock 720p","BLEED")
A14: Premium all 1080p | B14: =5*Assumptions!$B$32 | C14: =99-B14 | D14: =IF(C14>=0,"OK","BLEED — soft-cap 1080p or boost pack")
A15: Premium Pro all 1080p | B15: =10*Assumptions!$B$32 | C15: =199-B15 | D15: =IF(C15>=0,"OK","BLEED")

Sheet RTC Packs
A1: OVERAGE PACKS — REVENUE & MARGIN
A3: Pack | B3: RTC | C3: Sets equiv | D3: Price $ | E3: COGS @720p | F3: COGS @1080p | G3: Margin 720p | H3: Margin 1080p | I3: vs list $7.99
A4: pack_10 | B4: 10 | C4: =B4/Assumptions!$B$17 | D4: 69 | E4: =C4*Assumptions!$B$30 | F4: =C4*Assumptions!$B$32 | G4: =D4-E4 | H4: =D4-F4 | I4: =D4-(B4*Assumptions!$B$18)
A5: pack_25 | B5: 25 | C5: =B5/Assumptions!$B$17 | D5: 149 | E5: =C5*Assumptions!$B$30 | F5: =C5*Assumptions!$B$32 | G5: =D5-E5 | H5: =D5-F5 | I5: =D5-(B5*Assumptions!$B$18)
A6: pack_50 | B6: 50 | C6: =B6/Assumptions!$B$17 | D6: 269 | E6: =C6*Assumptions!$B$30 | F6: =C6*Assumptions!$B$32 | G6: =D6-E6 | H6: =D6-F6 | I6: =D6-(B6*Assumptions!$B$18)
A8: Packs beat list price for buyer but still clear margin if Cost Saver / 720p. Viral months = pack revenue.

Sheet Portfolio Scenario
A1: MONTHLY PORTFOLIO — SUBSCRIBERS × TIER
A2: Edit yellow subscriber counts. Revenue/COGS/margin formulas pull Tier P&L unit economics.
A4: Tier | B4: Subscribers | C4: MRR $ | D4: COGS $ | E4: Gross profit $ | F4: Notes
A5: Free Test | B5: 200 | C5: =B5*='Tier P&L'!B5 | D5: =B5*='Tier P&L'!H5 | E5: =C5-D5 | F5: CAC drain; conversion lever Assumptions!B23
A6: Basic | B6: 40 | C6: =B6*='Tier P&L'!B6 | D6: =B6*='Tier P&L'!H6 | E6: =C6-D6
A7: Premium ★ | B7: 25 | C7: =B7*='Tier P&L'!B7 | D7: =B7*='Tier P&L'!H7 | E7: =C7-D7 | F7: Hero volume
A8: Premium Pro | B8: 8 | C8: =B8*='Tier P&L'!B8 | D8: =B8*='Tier P&L'!H8 | E8: =C8-D8
A10: Subscription totals | B10: =SUM(B5:B8) | C10: =SUM(C5:C8) | D10: =SUM(D5:D8) | E10: =SUM(E5:E8)
A12: Add: RTC pack sales (estimate) | B12: 6 | C12: 149 | D12: =B12*C12 | E12: Pack units × avg pack price (edit)
A13: Pack COGS estimate (720p) | D13: =B12*(25/Assumptions!$B$17)*Assumptions!$B$30
A15: Fixed platform opex | D15: ='API Subscriptions'!E20
A17: NET MONTHLY (subs GP + pack GP − fixed opex) | D17: =E10+(D12-D13)-D15
A19: Free CAC burn | D19: =B5*'Tier P&L'!H5
A20: Implied Basic from Free (at CVR) | D20: =B5*Assumptions!B23
